[
	{
		"id": "lunch",
		"title": "Lunch Special",
		"subtitle": "Monday&ndash;Sunday 10am&ndash;3pm",
		"info": "All entrées served with <em>steamed rice, salad and soup</em>.<br />Fried vegetable spring roll or pork roll add $1.00 each.",
		"contents": [
			{
				"id": "L1",
				"type": "menuitem",
				"title": "Grilled Pork",
				"desc": "Topping with oyster sauce. Served with steamed broccoli",
				"price": 8
			},
			{
				"id": "L2",
				"type": "menuitem",
				"title": "Grilled Chicken Breast",
				"desc": "Topping with oyster sauce. Served with steamed broccoli",
				"price": 8
			},
			{
				"id": "L3",
				"type": "menuitem",
				"title": "Grilled Steak",
				"desc": "Topping with oyster sauce. Served with steamed broccoli",
				"price": 9
			},
			{
				"id": "L4",
				"type": "menuitem",
				"title": "Grilled Salmon",
				"desc": "Topping with shrimp, vegetable, and oyster sauce",
				"price": 11
			},
			{
				"id": "L5",
				"type": "menuitem",
				"title": "Grilled Shrimp",
				"desc": "Grilled shrimp on steamed broccoli with oyster sauce",
				"price": 10
			},
			{
				"id": "L6",
				"type": "menuitem",
				"title": "Tilapia",
				"desc": "Fried tilapia topping with shrimp, vegetable and basil",
				"price": 10
			},
			{
				"id": "L7",
				"type": "menuitem",
				"title": "Chicken Rote",
				"desc": "Stir fried sliced chicken with yellow powder over steamed broccoli",
				"price": 8
			},
			{
				"id": "L8",
				"type": "menuitem",
				"title": "Himalaya Chicken",
				"desc": "Stir fried sliced chicken with cashew nut and vegetable",
				"price": 8
			},
			{
				"id": "L9",
				"type": "menuitem",
				"title": "Beef with Oyster Sauce",
				"desc": "Sauteed sliced beef, onion, carrot and asparagus with oyster sauce",
				"price": 10
			},
			{
				"id": "L10",
				"type": "menuitem",
				"title": "Basil",
				"desc": "Pan fried hot pepper, vegetable and basil with a choice of:",
				"options": [
					{
						"title": "Vegetable or chicken",
						"price": 8
					},
					{
						"title": "Beef",
						"price": 9
					},
					{
						"title": "Seafood",
						"price": 11
					}
				]
			},
			{
				"id": "L11",
				"type": "menuitem",
				"title": "Ginger",
				"desc": "Stir fried fresh ginger, vegetable with a choice of:",
				"options": [
					{
						"title": "Vegetable or chicken",
						"price": 8
					},
					{
						"title": "Beef",
						"price": 9
					},
					{
						"title": "Seafood",
						"price": 11
					}
				]
			},
			{
				"id": "L12",
				"type": "menuitem",
				"title": "Curry",
				"desc": "Curry paste, coconut milk, vegetable with a choice of:",
				"options": [
					{
						"title": "Vegetable or chicken",
						"price": 8
					},
					{
						"title": "Beef",
						"price": 9
					},
					{
						"title": "Seafood",
						"price": 11
					}
				]
			},
			{
				"id": "L13",
				"type": "menuitem",
				"title": "Sweet & Sour",
				"desc": "Sautéed pineapple, tomato, and cucumber with a choice of:",
				"options": [
					{
						"title": "Vegetable or chicken",
						"price": 8
					},
					{
						"title": "Beef",
						"price": 9
					},
					{
						"title": "Seafood",
						"price": 11
					}
				]
			}
		]
	},
	{
		"id": "beverages",
		"title": "Beverages",
		"contents": [
			{
				"id": "B1",
				"type": "menuitem",
				"title": "Thai Ice Tea, Thai Ice Coffee",
				"price": 3
			},
			{
				"id": "B2",
				"type": "menuitem",
				"title": "Soft Drinks, Milk",
				"price": 2
			},
			{
				"id": "B3",
				"type": "menuitem",
				"title": "Bottle Water",
				"price": 1.85
			},
			{
				"id": "B4",
				"type": "menuitem",
				"title": "Perrier",
				"price": 2.6
			},
			{
				"id": "B5",
				"type": "menuitem",
				"title": "Coffee, Ice Tea, Hot Green Tea (free refill)",
				"price": 2
			},
			{
				"id": "B6",
				"type": "menuitem",
				"title": "Juice &ndash; Orange, Cranberry, Apple",
				"price": 2.5
			},
			{
				"id": "B7",
				"type": "menuitem",
				"title": "Chocolate Milk, Hot Chocolate",
				"price": 2
			}
		]
	},
	{
		"id": "appetizers",
		"title": "Appetizers",
		"contents": [
			{
				"id": "A1",
				"type": "menuitem",
				"title": "Golden Soft Shell Crab",
				"desc": "Soft shell crab and asparagus seasoned in light batter, deep fried. Served with sweet chili sauce.",
				"price": 11
			},
			{
				"id": "A3",
				"type": "menuitem",
				"title": "Calamari",
				"desc": "Squid in seasoned tempura batter fried to perfection. Served with sweet chili sauce.",
				"price": 9
			},
			{
				"id": "A4",
				"type": "menuitem",
				"title": "Grill Squid",
				"desc": "BBQ whole squid, sliced top with house-made sauce",
				"price": 10
			},
			{
				"id": "A5",
				"type": "menuitem",
				"title": "Fresh Spring Roll",
				"desc": "Mixed green vegetables, cucumber, tofu, cilantro, rolled in rice paper topped with sweet chili sauce.",
				"price": 7,
				"options": [
					{
						"title": "Add chicken or beef $1 extra"
					},
					{
						"title": "Add shrimp $1.75 extra"
					}
				]
			},
			{
				"id": "A6",
				"type": "menuitem",
				"title": "Shrimp Toast",
				"desc": "Deep fried little triangle shape bread stuffed with minced shrimp and chicken. Served with crush peanut in sweet chili sauce.",
				"price": 7
			},
			{
				"id": "A7",
				"type": "menuitem",
				"title": "Shrimp in Blanket",
				"desc": "Crispy fried shrimp and minced chicken wrapped in bacon. Served with sweet chili sauce.",
				"price": 7
			},
			{
				"id": "A8",
				"type": "menuitem",
				"title": "Shumai",
				"desc": "Small steamed dumplings stuffed with shrimp and chicken and served with light vinegar sauce.",
				"price": 6
			},
			{
				"id": "A9",
				"type": "menuitem",
				"title": "Satay (Chicken or Pork)",
				"desc": "Marinated and lightly grilled, braised with coconut milk. Served with peanut sauce and cucumber salad",
				"price": 8
			},
			{
				"id": "A10",
				"type": "menuitem",
				"title": "BBQ Ribs",
				"desc": "Marinated rib with homemade barbecued sauce.",
				"price": 7
			},
			{
				"id": "A11",
				"type": "menuitem",
				"title": "Fried Spring Rolls",
				"desc": "Crispy fried spring rolls stuffed with minced pork, glass noodle, shredded carrots, and woo dear mushroom. Served with sweet chili sauce.",
				"price": 6
			},
			{
				"id": "A12",
				"type": "menuitem",
				"title": "Fried Wonton",
				"desc": "Wonton skin stuffed with minced chicken and shrimp",
				"price": 6
			},
			{
				"id": "A13",
				"type": "menuitem",
				"title": "Crispy Tofu",
				"desc": "Deep fried fresh triangle bean curd. Served with sweet chili sauce and crushed peanut.",
				"price": 5
			},
			{
				"id": "A14",
				"type": "menuitem",
				"title": "Fried Vegetarian Spring Rolls",
				"desc": "Crispy fried spring roll stuffed with assorted vegetable, glass noodle. Served with sweet chili sauce.",
				"price": 4
			},
			{
				"id": "A15",
				"type": "menuitem",
				"title": "Edamame",
				"desc": "Steamed soy beans.",
				"price": 5
			}
		]
	},
	{
		"id": "entrees",
		"title": "Entrées",
		"info": "All entrées served with steamed rice (brown rice add 75&cent;)",
		"contents": [
			{
				"id": "E1",
				"type": "menuitem",
				"title": "Tilapia",
				"desc": "Battered, deep fried tilapia, topped off with sautéed shrimp and choice of basil or ginger or sweet & sour sauce.",
				"price": 12
			},
			{
				"id": "E2",
				"type": "menuitem",
				"title": "Grilled Salmon",
				"desc": "Grilled salmon and shrimp topped with sautéed vegetable and oyster sauce.",
				"price": 13
			},
			{
				"id": "E3",
				"type": "menuitem",
				"title": "Golden Eggplant",
				"desc": "Battered, deep fried eggplant, topped off with sautéed shrimp, crawfish, vegetable and curry paste.",
				"price": 13
			},
			{
				"id": "E4",
				"type": "menuitem",
				"title": "Garlic Shrimp",
				"desc": "Grilled shrimp on steamed broccoli bed topped with garlic sauce.",
				"price": 11
			},
			{
				"id": "E5",
				"type": "menuitem",
				"title": "Beef Asparagus",
				"desc": "Sautéed beef with asparagus, carrots, and onions in oyster sauce.",
				"price": 10
			},
			{
				"id": "E6",
				"type": "menuitem",
				"title": "Himalaya Chicken",
				"desc": "Sautéed chicken breast with onions, carrots, roasted cashew nuts and scallions in our house special sauce",
				"price": 9
			},
			{
				"id": "E7",
				"type": "menuitem",
				"title": "Garlic Pepper Chicken",
				"desc": "Choice of sliced chicken or sliced beef sautéed with garlic and white peppers on a bed of steamed broccoli.",
				"options": [
					{
						"title": "Chicken",
						"price": 9
					},
					{
						"title": "Beef",
						"price": 10
					}
				]
			},
			{
				"id": "curry-info-1",
				"type": "menuinfo",
				"info": "For following dishes, choose vegetable $9, chicken $10, beef $10, shrimp $11, seafood $13."
			},
			{
				"id": "E8",
				"type": "menuitem",
				"title": "Red Curry",
				"desc": "Choice of meat or seafood in red curry with coconut milk, bamboo, carrots, onions, bell peppers and basil leaves.",
				"price": 12
			},
			{
				"id": "E9",
				"type": "menuitem",
				"title": "Green Curry",
				"desc": "Choice of meat or seafood in green curry with coconut milk, bamboo, carrots, onions, bell peppers and basil leaves."
			},
			{
				"id": "E10",
				"type": "menuitem",
				"title": "Panang Curry",
				"desc": "Panang curry paste slowly simmered in creamy coconut milk with bell peppers, lime leaves, and chioce of meat or seafood."
			},
			{
				"id": "E11",
				"type": "menuitem",
				"title": "Massamun Curry",
				"desc": "Choice of meat or seafood cooked in massamun curry with coconut milk, onions, potatoes and peanuts."
			},
			{
				"id": "curry-info-2",
				"type": "menuinfo",
				"info": "For following dishes, choose vegetable $9, chicken $9, beef $10, shrimp $11, seafood $13."
			},
			{
				"id": "E12",
				"type": "menuitem",
				"title": "Pad Ped Curry",
				"desc": "Spicy curry paste sautéed with carrots, bell peppers, bamboo, basil leaves, lime leaves, with your choice of meat or seafood.",
				"price": 9
			},
			{
				"id": "E13",
				"type": "menuitem",
				"title": "Basil",
				"desc": "Chili garlic sauce wiht fresh basil leaves, onions, carrots and bell pepers, and choice of meat or seafood"
			},
			{
				"id": "E14",
				"type": "menuitem",
				"title": "Ginger",
				"desc": "Choice of meat or seafood stir-fried with fresh ginger, onions, scallions and black mushrooms in soy bean sauce."
			},
			{
				"id": "E15",
				"type": "menuitem",
				"title": "Sweet & Sour",
				"desc": "Choice of meat or seafood sautéd with tomatoes, pineapples, cucumbers and onions."
			}
		]
	},
	{
		"id": "soups",
		"title": "Entrées",
		"info": "All entrées served with steamed rice (brown rice add 75&cent;)",
		"contents": [
			{
				"id": "E1",
				"type": "menuitem",
				"title": "Tilapia",
				"desc": "Battered, deep fried tilapia, topped off with sautéed shrimp and choice of basil or ginger or sweet & sour sauce.",
				"price": 12
			},
			{
				"id": "E2",
				"type": "menuitem",
				"title": "Grilled Salmon",
				"desc": "Grilled salmon and shrimp topped with sautéed vegetable and oyster sauce.",
				"price": 13
			},
			{
				"id": "E3",
				"type": "menuitem",
				"title": "Golden Eggplant",
				"desc": "Battered, deep fried eggplant, topped off with sautéed shrimp, crawfish, vegetable and curry paste.",
				"price": 13
			},
			{
				"id": "E4",
				"type": "menuitem",
				"title": "Garlic Shrimp",
				"desc": "Grilled shrimp on steamed broccoli bed topped with garlic sauce.",
				"price": 11
			},
			{
				"id": "E5",
				"type": "menuitem",
				"title": "Beef Asparagus",
				"desc": "Sautéed beef with asparagus, carrots, and onions in oyster sauce.",
				"price": 10
			},
			{
				"id": "E6",
				"type": "menuitem",
				"title": "Himalaya Chicken",
				"desc": "Sautéed chicken breast with onions, carrots, roasted cashew nuts and scallions in our house special sauce",
				"price": 9
			},
			{
				"id": "E7",
				"type": "menuitem",
				"title": "Garlic Pepper Chicken",
				"desc": "Choice of sliced chicken or sliced beef sautéed with garlic and white peppers on a bed of steamed broccoli.",
				"options": [
					{
						"title": "Chicken",
						"price": 9
					},
					{
						"title": "Beef",
						"price": 10
					}
				]
			}
		]
	}
]
